backlib/__init__.py
backlib/cache/aprilmenu__4866825.mp3
backlib/cache/bleepsgalore__4355204.mp3
backlib/cache/boss1__2566868.ogg
backlib/cache/boss2__2705612.ogg
backlib/cache/credits__3596955.mp3
backlib/cache/day4__1866532.mp3
backlib/cache/editor__1539857.ogg
backlib/cache/fine__1819566.ogg
backlib/cache/game1__1281219.ogg
hyperpool2-0.0.0.1.dist-info/METADATA
hyperpool2-0.0.0.1.dist-info/WHEEL
hyperpool2-0.0.0.1.dist-info/licenses/LICENSE
hyperpool2-0.0.0.1.dist-info/RECORD
